jalali_date_new/__init__.py
jalali_date_new/admin.py
jalali_date_new/fields.py
jalali_date_new/model_fields.py
jalali_date_new/utils.py
jalali_date_new/widgets.py
jalali_date_new/static/jalali_date_new/css/jalalidatepicker.min.css
jalali_date_new/static/jalali_date_new/js/datepicker.js
jalali_date_new/static/jalali_date_new/js/jalalidatepicker.min.js
jalali_date_new/templates/jalali_date_new/widgets/jalalidate.html
jalali_date_new/templates/jalali_date_new/widgets/jalalidatetime.html
jalali_date_new/templates/jalali_date_new/widgets/jalalitime.html
Django_jalali_date_new-1.1.dist-info/LICENSE
Django_jalali_date_new-1.1.dist-info/METADATA
Django_jalali_date_new-1.1.dist-info/WHEEL
Django_jalali_date_new-1.1.dist-info/top_level.txt
Django_jalali_date_new-1.1.dist-info/RECORD
