Metadata-Version: 2.1
Name: Django-jalali-date-new
Version: 1.1
Summary: With this package you can use persian calendar in admin interface and views
Author-email: navid shaghouzaei <navid.shagho003@gmail.com>
Project-URL: Homepage, https://github.com/shagho/Django-jalali-date-new
Project-URL: Issues, https://github.com/shagho/Django-jalali-date-new/issues
Classifier: Programming Language :: Python :: 3
Classifier: License :: OSI Approved :: MIT License
Classifier: Operating System :: OS Independent
Requires-Python: >=3.8
License-File: LICENSE
Requires-Dist: django>=2.2
Requires-Dist: jdatetime>=4.1.1
